Workbook

Sheet Model
A1: PACT - how a subclass bonus-spell bundle is priced
A3: Engine rules version (js/engine-data.js) | B3: v0.347
A5: READ THIS FIRST - is the origin discount applied twice?
A6: No. A bundle is charged with ONE lookup: engine.js does `_isO ? bundle.origin : bundle.cross`. It
A7: picks one of two stored numbers and never subtracts a discount from either, so there is no second
A8: application to be had. The discount is applied once, when the stored `origin` figure was derived -
A9: and the 'Per-spell working' sheet reproduces that derivation from the real spell lists.
A11: The direct check is the ORIGIN GAP (cross - origin) on the Bundles sheet. If the discount were being
A12: applied twice, the engine's gap would exceed the model's gap. On all 21 bundles it does not - column
A13: N reads 'applied exactly once' for every one.
A15: What DOES look wrong side by side, and isn't: the guide's ability tables head column 3 'Sticker
A16: (Origin)'. For an ordinary class feature the sticker is already reduced - sticker = cross - tier. A
A17: bundle has no tier, so nothing is subtracted and the sticker equals the full cross price. Both mean
A18: 'what a non-origin member of that class pays'; they are just reached differently. See 'Price paths'.
A20: Inputs (blue = hardcoded here, green = read from the engine)
A21: Origin discount, AP per spell | B21: 1
A22: Floor - no spell can cost less than this | B22: 1
A23: Cantrip granted by a bundle, flat AP each (no discount) | B23: 4
A24: Grants unlocking above this character level ride free | B24: 5
A26: AP per spell known, by spell level (DATA.knownUnit)
A27: 1 | B27: 1
A28: 2 | B28: 1
A29: 3 | B29: 2
A30: 4 | B30: 2
A31: 5 | B31: 3
A32: 6 | B32: 3
A33: 7 | B33: 4
A34: 8 | B34: 4
A35: 9 | B35: 5
A37: Where the spell lists come from
A38: DATA.spellGrants.subclassSpells - the engine's own index of every 2024 ability that grants spells,
A39: with each spell's level and the character level its grant unlocks at. Nothing here is reconstructed.
A40: This reproduces 20 of the 21 stored prices exactly; Circle of the Sea is the single miss (charged
A41: 11/9 where its seven paid grants total 12/10 - the same shape as Aberrant Sorcery, charged 12/10).

Sheet Per-spell working
A1: Key | B1: Class | C1: Subclass | D1: Spell | E1: Spell level (0 = cantrip) | F1: Unlocks at char level | G1: Paid or free | H1: Cross AP | I1: Origin AP (-1, floored at 1) | J1: Discount saved
A2: Cleric|Life Domain | B2: Cleric | C2: Life Domain | D2: Aid | E2: 2 | F2: 3 | G2: =IF(F2<=Model!$B$24,"PAID","free with bundle") | H2: =VLOOKUP(E2,Model!$A$27:$B$35,2,FALSE) | I2: =MAX(Model!$B$22,H2-Model!$B$21) | J2: =H2-I2
A3: Cleric|Life Domain | B3: Cleric | C3: Life Domain | D3: Bless | E3: 1 | F3: 3 | G3: =IF(F3<=Model!$B$24,"PAID","free with bundle") | H3: =VLOOKUP(E3,Model!$A$27:$B$35,2,FALSE) | I3: =MAX(Model!$B$22,H3-Model!$B$21) | J3: =H3-I3
A4: Cleric|Life Domain | B4: Cleric | C4: Life Domain | D4: Cure Wounds | E4: 1 | F4: 3 | G4: =IF(F4<=Model!$B$24,"PAID","free with bundle") | H4: =VLOOKUP(E4,Model!$A$27:$B$35,2,FALSE) | I4: =MAX(Model!$B$22,H4-Model!$B$21) | J4: =H4-I4
A5: Cleric|Life Domain | B5: Cleric | C5: Life Domain | D5: Lesser Restoration | E5: 2 | F5: 3 | G5: =IF(F5<=Model!$B$24,"PAID","free with bundle") | H5: =VLOOKUP(E5,Model!$A$27:$B$35,2,FALSE) | I5: =MAX(Model!$B$22,H5-Model!$B$21) | J5: =H5-I5
A6: Cleric|Life Domain | B6: Cleric | C6: Life Domain | D6: Mass Healing Word | E6: 3 | F6: 5 | G6: =IF(F6<=Model!$B$24,"PAID","free with bundle") | H6: =VLOOKUP(E6,Model!$A$27:$B$35,2,FALSE) | I6: =MAX(Model!$B$22,H6-Model!$B$21) | J6: =H6-I6
A7: Cleric|Life Domain | B7: Cleric | C7: Life Domain | D7: Revivify | E7: 3 | F7: 5 | G7: =IF(F7<=Model!$B$24,"PAID","free with bundle") | H7: =VLOOKUP(E7,Model!$A$27:$B$35,2,FALSE) | I7: =MAX(Model!$B$22,H7-Model!$B$21) | J7: =H7-I7
A8: Cleric|Life Domain | B8: Cleric | C8: Life Domain | D8: Aura of Life | E8: 4 | F8: 7 | G8: =IF(F8<=Model!$B$24,"PAID","free with bundle") | H8: 0 | I8: 0 | J8: =H8-I8
A9: Cleric|Life Domain | B9: Cleric | C9: Life Domain | D9: Death Ward | E9: 4 | F9: 7 | G9: =IF(F9<=Model!$B$24,"PAID","free with bundle") | H9: 0 | I9: 0 | J9: =H9-I9
A10: Cleric|Life Domain | B10: Cleric | C10: Life Domain | D10: Greater Restoration | E10: 5 | F10: 9 | G10: =IF(F10<=Model!$B$24,"PAID","free with bundle") | H10: 0 | I10: 0 | J10: =H10-I10
A11: Cleric|Life Domain | B11: Cleric | C11: Life Domain | D11: Mass Cure Wounds | E11: 5 | F11: 9 | G11: =IF(F11<=Model!$B$24,"PAID","free with bundle") | H11: 0 | I11: 0 | J11: =H11-I11
A12: Cleric|Light Domain | B12: Cleric | C12: Light Domain | D12: Burning Hands | E12: 1 | F12: 3 | G12: =IF(F12<=Model!$B$24,"PAID","free with bundle") | H12: =VLOOKUP(E12,Model!$A$27:$B$35,2,FALSE) | I12: =MAX(Model!$B$22,H12-Model!$B$21) | J12: =H12-I12
A13: Cleric|Light Domain | B13: Cleric | C13: Light Domain | D13: Faerie Fire | E13: 1 | F13: 3 | G13: =IF(F13<=Model!$B$24,"PAID","free with bundle") | H13: =VLOOKUP(E13,Model!$A$27:$B$35,2,FALSE) | I13: =MAX(Model!$B$22,H13-Model!$B$21) | J13: =H13-I13
A14: Cleric|Light Domain | B14: Cleric | C14: Light Domain | D14: Scorching Ray | E14: 2 | F14: 3 | G14: =IF(F14<=Model!$B$24,"PAID","free with bundle") | H14: =VLOOKUP(E14,Model!$A$27:$B$35,2,FALSE) | I14: =MAX(Model!$B$22,H14-Model!$B$21) | J14: =H14-I14
A15: Cleric|Light Domain | B15: Cleric | C15: Light Domain | D15: See Invisibility | E15: 2 | F15: 3 | G15: =IF(F15<=Model!$B$24,"PAID","free with bundle") | H15: =VLOOKUP(E15,Model!$A$27:$B$35,2,FALSE) | I15: =MAX(Model!$B$22,H15-Model!$B$21) | J15: =H15-I15
A16: Cleric|Light Domain | B16: Cleric | C16: Light Domain | D16: Daylight | E16: 3 | F16: 5 | G16: =IF(F16<=Model!$B$24,"PAID","free with bundle") | H16: =VLOOKUP(E16,Model!$A$27:$B$35,2,FALSE) | I16: =MAX(Model!$B$22,H16-Model!$B$21) | J16: =H16-I16
A17: Cleric|Light Domain | B17: Cleric | C17: Light Domain | D17: Fireball | E17: 3 | F17: 5 | G17: =IF(F17<=Model!$B$24,"PAID","free with bundle") | H17: =VLOOKUP(E17,Model!$A$27:$B$35,2,FALSE) | I17: =MAX(Model!$B$22,H17-Model!$B$21) | J17: =H17-I17
A18: Cleric|Light Domain | B18: Cleric | C18: Light Domain | D18: Arcane Eye | E18: 4 | F18: 7 | G18: =IF(F18<=Model!$B$24,"PAID","free with bundle") | H18: 0 | I18: 0 | J18: =H18-I18
A19: Cleric|Light Domain | B19: Cleric | C19: Light Domain | D19: Wall of Fire | E19: 4 | F19: 7 | G19: =IF(F19<=Model!$B$24,"PAID","free with bundle") | H19: 0 | I19: 0 | J19: =H19-I19
A20: Cleric|Light Domain | B20: Cleric | C20: Light Domain | D20: Flame Strike | E20: 5 | F20: 9 | G20: =IF(F20<=Model!$B$24,"PAID","free with bundle") | H20: 0 | I20: 0 | J20: =H20-I20
A21: Cleric|Light Domain | B21: Cleric | C21: Light Domain | D21: Scrying | E21: 5 | F21: 9 | G21: =IF(F21<=Model!$B$24,"PAID","free with bundle") | H21: 0 | I21: 0 | J21: =H21-I21
A22: Cleric|Trickery Domain | B22: Cleric | C22: Trickery Domain | D22: Charm Person | E22: 1 | F22: 3 | G22: =IF(F22<=Model!$B$24,"PAID","free with bundle") | H22: =VLOOKUP(E22,Model!$A$27:$B$35,2,FALSE) | I22: =MAX(Model!$B$22,H22-Model!$B$21) | J22: =H22-I22
A23: Cleric|Trickery Domain | B23: Cleric | C23: Trickery Domain | D23: Disguise Self | E23: 1 | F23: 3 | G23: =IF(F23<=Model!$B$24,"PAID","free with bundle") | H23: =VLOOKUP(E23,Model!$A$27:$B$35,2,FALSE) | I23: =MAX(Model!$B$22,H23-Model!$B$21) | J23: =H23-I23
A24: Cleric|Trickery Domain | B24: Cleric | C24: Trickery Domain | D24: Invisibility | E24: 2 | F24: 3 | G24: =IF(F24<=Model!$B$24,"PAID","free with bundle") | H24: =VLOOKUP(E24,Model!$A$27:$B$35,2,FALSE) | I24: =MAX(Model!$B$22,H24-Model!$B$21) | J24: =H24-I24
A25: Cleric|Trickery Domain | B25: Cleric | C25: Trickery Domain | D25: Pass without Trace | E25: 2 | F25: 3 | G25: =IF(F25<=Model!$B$24,"PAID","free with bundle") | H25: =VLOOKUP(E25,Model!$A$27:$B$35,2,FALSE) | I25: =MAX(Model!$B$22,H25-Model!$B$21) | J25: =H25-I25
A26: Cleric|Trickery Domain | B26: Cleric | C26: Trickery Domain | D26: Hypnotic Pattern | E26: 3 | F26: 5 | G26: =IF(F26<=Model!$B$24,"PAID","free with bundle") | H26: =VLOOKUP(E26,Model!$A$27:$B$35,2,FALSE) | I26: =MAX(Model!$B$22,H26-Model!$B$21) | J26: =H26-I26
A27: Cleric|Trickery Domain | B27: Cleric | C27: Trickery Domain | D27: Nondetection | E27: 3 | F27: 5 | G27: =IF(F27<=Model!$B$24,"PAID","free with bundle") | H27: =VLOOKUP(E27,Model!$A$27:$B$35,2,FALSE) | I27: =MAX(Model!$B$22,H27-Model!$B$21) | J27: =H27-I27
A28: Cleric|Trickery Domain | B28: Cleric | C28: Trickery Domain | D28: Confusion | E28: 4 | F28: 7 | G28: =IF(F28<=Model!$B$24,"PAID","free with bundle") | H28: 0 | I28: 0 | J28: =H28-I28
A29: Cleric|Trickery Domain | B29: Cleric | C29: Trickery Domain | D29: Dimension Door | E29: 4 | F29: 7 | G29: =IF(F29<=Model!$B$24,"PAID","free with bundle") | H29: 0 | I29: 0 | J29: =H29-I29
A30: Cleric|Trickery Domain | B30: Cleric | C30: Trickery Domain | D30: Dominate Person | E30: 5 | F30: 9 | G30: =IF(F30<=Model!$B$24,"PAID","free with bundle") | H30: 0 | I30: 0 | J30: =H30-I30
A31: Cleric|Trickery Domain | B31: Cleric | C31: Trickery Domain | D31: Modify Memory | E31: 5 | F31: 9 | G31: =IF(F31<=Model!$B$24,"PAID","free with bundle") | H31: 0 | I31: 0 | J31: =H31-I31
A32: Cleric|War Domain | B32: Cleric | C32: War Domain | D32: Guiding Bolt | E32: 1 | F32: 3 | G32: =IF(F32<=Model!$B$24,"PAID","free with bundle") | H32: =VLOOKUP(E32,Model!$A$27:$B$35,2,FALSE) | I32: =MAX(Model!$B$22,H32-Model!$B$21) | J32: =H32-I32
A33: Cleric|War Domain | B33: Cleric | C33: War Domain | D33: Shield of Faith | E33: 1 | F33: 3 | G33: =IF(F33<=Model!$B$24,"PAID","free with bundle") | H33: =VLOOKUP(E33,Model!$A$27:$B$35,2,FALSE) | I33: =MAX(Model!$B$22,H33-Model!$B$21) | J33: =H33-I33
A34: Cleric|War Domain | B34: Cleric | C34: War Domain | D34: Magic Weapon | E34: 2 | F34: 3 | G34: =IF(F34<=Model!$B$24,"PAID","free with bundle") | H34: =VLOOKUP(E34,Model!$A$27:$B$35,2,FALSE) | I34: =MAX(Model!$B$22,H34-Model!$B$21) | J34: =H34-I34
A35: Cleric|War Domain | B35: Cleric | C35: War Domain | D35: Spiritual Weapon | E35: 2 | F35: 3 | G35: =IF(F35<=Model!$B$24,"PAID","free with bundle") | H35: =VLOOKUP(E35,Model!$A$27:$B$35,2,FALSE) | I35: =MAX(Model!$B$22,H35-Model!$B$21) | J35: =H35-I35
A36: Cleric|War Domain | B36: Cleric | C36: War Domain | D36: Crusader's Mantle | E36: 3 | F36: 5 | G36: =IF(F36<=Model!$B$24,"PAID","free with bundle") | H36: =VLOOKUP(E36,Model!$A$27:$B$35,2,FALSE) | I36: =MAX(Model!$B$22,H36-Model!$B$21) | J36: =H36-I36
A37: Cleric|War Domain | B37: Cleric | C37: War Domain | D37: Spirit Guardians | E37: 3 | F37: 5 | G37: =IF(F37<=Model!$B$24,"PAID","free with bundle") | H37: =VLOOKUP(E37,Model!$A$27:$B$35,2,FALSE) | I37: =MAX(Model!$B$22,H37-Model!$B$21) | J37: =H37-I37
A38: Cleric|War Domain | B38: Cleric | C38: War Domain | D38: Fire Shield | E38: 4 | F38: 7 | G38: =IF(F38<=Model!$B$24,"PAID","free with bundle") | H38: 0 | I38: 0 | J38: =H38-I38
A39: Cleric|War Domain | B39: Cleric | C39: War Domain | D39: Freedom of Movement | E39: 4 | F39: 7 | G39: =IF(F39<=Model!$B$24,"PAID","free with bundle") | H39: 0 | I39: 0 | J39: =H39-I39
A40: Cleric|War Domain | B40: Cleric | C40: War Domain | D40: Hold Monster | E40: 5 | F40: 9 | G40: =IF(F40<=Model!$B$24,"PAID","free with bundle") | H40: 0 | I40: 0 | J40: =H40-I40
A41: Cleric|War Domain | B41: Cleric | C41: War Domain | D41: Steel Wind Strike | E41: 5 | F41: 9 | G41: =IF(F41<=Model!$B$24,"PAID","free with bundle") | H41: 0 | I41: 0 | J41: =H41-I41
A42: Druid|Circle of the Land | B42: Druid | C42: Circle of the Land | D42: Blur | E42: 2 | F42: 3 | G42: =IF(F42<=Model!$B$24,"PAID","free with bundle") | H42: =VLOOKUP(E42,Model!$A$27:$B$35,2,FALSE) | I42: =MAX(Model!$B$22,H42-Model!$B$21) | J42: =H42-I42
A43: Druid|Circle of the Land | B43: Druid | C43: Circle of the Land | D43: Burning Hands | E43: 1 | F43: 3 | G43: =IF(F43<=Model!$B$24,"PAID","free with bundle") | H43: =VLOOKUP(E43,Model!$A$27:$B$35,2,FALSE) | I43: =MAX(Model!$B$22,H43-Model!$B$21) | J43: =H43-I43
A44: Druid|Circle of the Land | B44: Druid | C44: Circle of the Land | D44: Fire Bolt | E44: 0 | F44: 3 | G44: =IF(F44<=Model!$B$24,"PAID","free with bundle") | H44: =Model!$B$23 | I44: =Model!$B$23 | J44: =H44-I44
A45: Druid|Circle of the Land | B45: Druid | C45: Circle of the Land | D45: Fireball | E45: 3 | F45: 5 | G45: =IF(F45<=Model!$B$24,"PAID","free with bundle") | H45: =VLOOKUP(E45,Model!$A$27:$B$35,2,FALSE) | I45: =MAX(Model!$B$22,H45-Model!$B$21) | J45: =H45-I45
A46: Druid|Circle of the Land | B46: Druid | C46: Circle of the Land | D46: Blight | E46: 4 | F46: 7 | G46: =IF(F46<=Model!$B$24,"PAID","free with bundle") | H46: 0 | I46: 0 | J46: =H46-I46
A47: Druid|Circle of the Land | B47: Druid | C47: Circle of the Land | D47: Wall of Stone | E47: 5 | F47: 9 | G47: =IF(F47<=Model!$B$24,"PAID","free with bundle") | H47: 0 | I47: 0 | J47: =H47-I47
A48: Druid|Circle of the Moon | B48: Druid | C48: Circle of the Moon | D48: Cure Wounds | E48: 1 | F48: 3 | G48: =IF(F48<=Model!$B$24,"PAID","free with bundle") | H48: =VLOOKUP(E48,Model!$A$27:$B$35,2,FALSE) | I48: =MAX(Model!$B$22,H48-Model!$B$21) | J48: =H48-I48
A49: Druid|Circle of the Moon | B49: Druid | C49: Circle of the Moon | D49: Moonbeam | E49: 2 | F49: 3 | G49: =IF(F49<=Model!$B$24,"PAID","free with bundle") | H49: =VLOOKUP(E49,Model!$A$27:$B$35,2,FALSE) | I49: =MAX(Model!$B$22,H49-Model!$B$21) | J49: =H49-I49
A50: Druid|Circle of the Moon | B50: Druid | C50: Circle of the Moon | D50: Starry Wisp | E50: 0 | F50: 3 | G50: =IF(F50<=Model!$B$24,"PAID","free with bundle") | H50: =Model!$B$23 | I50: =Model!$B$23 | J50: =H50-I50
A51: Druid|Circle of the Moon | B51: Druid | C51: Circle of the Moon | D51: Conjure Animals | E51: 3 | F51: 5 | G51: =IF(F51<=Model!$B$24,"PAID","free with bundle") | H51: =VLOOKUP(E51,Model!$A$27:$B$35,2,FALSE) | I51: =MAX(Model!$B$22,H51-Model!$B$21) | J51: =H51-I51
A52: Druid|Circle of the Moon | B52: Druid | C52: Circle of the Moon | D52: Fount of Moonlight | E52: 4 | F52: 7 | G52: =IF(F52<=Model!$B$24,"PAID","free with bundle") | H52: 0 | I52: 0 | J52: =H52-I52
A53: Druid|Circle of the Moon | B53: Druid | C53: Circle of the Moon | D53: Mass Cure Wounds | E53: 5 | F53: 9 | G53: =IF(F53<=Model!$B$24,"PAID","free with bundle") | H53: 0 | I53: 0 | J53: =H53-I53
A54: Druid|Circle of the Sea | B54: Druid | C54: Circle of the Sea | D54: Fog Cloud | E54: 1 | F54: 3 | G54: =IF(F54<=Model!$B$24,"PAID","free with bundle") | H54: =VLOOKUP(E54,Model!$A$27:$B$35,2,FALSE) | I54: =MAX(Model!$B$22,H54-Model!$B$21) | J54: =H54-I54
A55: Druid|Circle of the Sea | B55: Druid | C55: Circle of the Sea | D55: Gust of Wind | E55: 2 | F55: 3 | G55: =IF(F55<=Model!$B$24,"PAID","free with bundle") | H55: =VLOOKUP(E55,Model!$A$27:$B$35,2,FALSE) | I55: =MAX(Model!$B$22,H55-Model!$B$21) | J55: =H55-I55
A56: Druid|Circle of the Sea | B56: Druid | C56: Circle of the Sea | D56: Ray of Frost | E56: 0 | F56: 3 | G56: =IF(F56<=Model!$B$24,"PAID","free with bundle") | H56: =Model!$B$23 | I56: =Model!$B$23 | J56: =H56-I56
A57: Druid|Circle of the Sea | B57: Druid | C57: Circle of the Sea | D57: Shatter | E57: 2 | F57: 3 | G57: =IF(F57<=Model!$B$24,"PAID","free with bundle") | H57: =VLOOKUP(E57,Model!$A$27:$B$35,2,FALSE) | I57: =MAX(Model!$B$22,H57-Model!$B$21) | J57: =H57-I57
A58: Druid|Circle of the Sea | B58: Druid | C58: Circle of the Sea | D58: Thunderwave | E58: 1 | F58: 3 | G58: =IF(F58<=Model!$B$24,"PAID","free with bundle") | H58: =VLOOKUP(E58,Model!$A$27:$B$35,2,FALSE) | I58: =MAX(Model!$B$22,H58-Model!$B$21) | J58: =H58-I58
A59: Druid|Circle of the Sea | B59: Druid | C59: Circle of the Sea | D59: Lightning Bolt | E59: 3 | F59: 5 | G59: =IF(F59<=Model!$B$24,"PAID","free with bundle") | H59: =VLOOKUP(E59,Model!$A$27:$B$35,2,FALSE) | I59: =MAX(Model!$B$22,H59-Model!$B$21) | J59: =H59-I59
A60: Druid|Circle of the Sea | B60: Druid | C60: Circle of the Sea | D60: Water Breathing | E60: 3 | F60: 5 | G60: =IF(F60<=Model!$B$24,"PAID","free with bundle") | H60: =VLOOKUP(E60,Model!$A$27:$B$35,2,FALSE) | I60: =MAX(Model!$B$22,H60-Model!$B$21) | J60: =H60-I60
A61: Druid|Circle of the Sea | B61: Druid | C61: Circle of the Sea | D61: Control Water | E61: 4 | F61: 7 | G61: =IF(F61<=Model!$B$24,"PAID","free with bundle") | H61: 0 | I61: 0 | J61: =H61-I61
A62: Druid|Circle of the Sea | B62: Druid | C62: Circle of the Sea | D62: Ice Storm | E62: 4 | F62: 7 | G62: =IF(F62<=Model!$B$24,"PAID","free with bundle") | H62: 0 | I62: 0 | J62: =H62-I62
A63: Druid|Circle of the Sea | B63: Druid | C63: Circle of the Sea | D63: Conjure Elemental | E63: 5 | F63: 9 | G63: =IF(F63<=Model!$B$24,"PAID","free with bundle") | H63: 0 | I63: 0 | J63: =H63-I63
A64: Druid|Circle of the Sea | B64: Druid | C64: Circle of the Sea | D64: Hold Monster | E64: 5 | F64: 9 | G64: =IF(F64<=Model!$B$24,"PAID","free with bundle") | H64: 0 | I64: 0 | J64: =H64-I64
A65: Druid|Circle of the Stars | B65: Druid | C65: Circle of the Stars | D65: Guidance | E65: 0 | F65: 3 | G65: =IF(F65<=Model!$B$24,"PAID","free with bundle") | H65: =Model!$B$23 | I65: =Model!$B$23 | J65: =H65-I65
A66: Druid|Circle of the Stars | B66: Druid | C66: Circle of the Stars | D66: Guiding Bolt | E66: 1 | F66: 3 | G66: =IF(F66<=Model!$B$24,"PAID","free with bundle") | H66: =VLOOKUP(E66,Model!$A$27:$B$35,2,FALSE) | I66: =MAX(Model!$B$22,H66-Model!$B$21) | J66: =H66-I66
A67: Paladin|Oath of Devotion | B67: Paladin | C67: Oath of Devotion | D67: Protection from Evil and Good | E67: 1 | F67: 3 | G67: =IF(F67<=Model!$B$24,"PAID","free with bundle") | H67: =VLOOKUP(E67,Model!$A$27:$B$35,2,FALSE) | I67: =MAX(Model!$B$22,H67-Model!$B$21) | J67: =H67-I67
A68: Paladin|Oath of Devotion | B68: Paladin | C68: Oath of Devotion | D68: Shield of Faith | E68: 1 | F68: 3 | G68: =IF(F68<=Model!$B$24,"PAID","free with bundle") | H68: =VLOOKUP(E68,Model!$A$27:$B$35,2,FALSE) | I68: =MAX(Model!$B$22,H68-Model!$B$21) | J68: =H68-I68
A69: Paladin|Oath of Devotion | B69: Paladin | C69: Oath of Devotion | D69: Aid | E69: 2 | F69: 5 | G69: =IF(F69<=Model!$B$24,"PAID","free with bundle") | H69: =VLOOKUP(E69,Model!$A$27:$B$35,2,FALSE) | I69: =MAX(Model!$B$22,H69-Model!$B$21) | J69: =H69-I69
A70: Paladin|Oath of Devotion | B70: Paladin | C70: Oath of Devotion | D70: Zone of Truth | E70: 2 | F70: 5 | G70: =IF(F70<=Model!$B$24,"PAID","free with bundle") | H70: =VLOOKUP(E70,Model!$A$27:$B$35,2,FALSE) | I70: =MAX(Model!$B$22,H70-Model!$B$21) | J70: =H70-I70
A71: Paladin|Oath of Devotion | B71: Paladin | C71: Oath of Devotion | D71: Beacon of Hope | E71: 3 | F71: 9 | G71: =IF(F71<=Model!$B$24,"PAID","free with bundle") | H71: 0 | I71: 0 | J71: =H71-I71
A72: Paladin|Oath of Devotion | B72: Paladin | C72: Oath of Devotion | D72: Dispel Magic | E72: 3 | F72: 9 | G72: =IF(F72<=Model!$B$24,"PAID","free with bundle") | H72: 0 | I72: 0 | J72: =H72-I72
A73: Paladin|Oath of Devotion | B73: Paladin | C73: Oath of Devotion | D73: Freedom of Movement | E73: 4 | F73: 13 | G73: =IF(F73<=Model!$B$24,"PAID","free with bundle") | H73: 0 | I73: 0 | J73: =H73-I73
A74: Paladin|Oath of Devotion | B74: Paladin | C74: Oath of Devotion | D74: Guardian of Faith | E74: 4 | F74: 13 | G74: =IF(F74<=Model!$B$24,"PAID","free with bundle") | H74: 0 | I74: 0 | J74: =H74-I74
A75: Paladin|Oath of Devotion | B75: Paladin | C75: Oath of Devotion | D75: Commune | E75: 5 | F75: 17 | G75: =IF(F75<=Model!$B$24,"PAID","free with bundle") | H75: 0 | I75: 0 | J75: =H75-I75
A76: Paladin|Oath of Devotion | B76: Paladin | C76: Oath of Devotion | D76: Flame Strike | E76: 5 | F76: 17 | G76: =IF(F76<=Model!$B$24,"PAID","free with bundle") | H76: 0 | I76: 0 | J76: =H76-I76
A77: Paladin|Oath of Glory | B77: Paladin | C77: Oath of Glory | D77: Guiding Bolt | E77: 1 | F77: 3 | G77: =IF(F77<=Model!$B$24,"PAID","free with bundle") | H77: =VLOOKUP(E77,Model!$A$27:$B$35,2,FALSE) | I77: =MAX(Model!$B$22,H77-Model!$B$21) | J77: =H77-I77
A78: Paladin|Oath of Glory | B78: Paladin | C78: Oath of Glory | D78: Heroism | E78: 1 | F78: 3 | G78: =IF(F78<=Model!$B$24,"PAID","free with bundle") | H78: =VLOOKUP(E78,Model!$A$27:$B$35,2,FALSE) | I78: =MAX(Model!$B$22,H78-Model!$B$21) | J78: =H78-I78
A79: Paladin|Oath of Glory | B79: Paladin | C79: Oath of Glory | D79: Enhance Ability | E79: 2 | F79: 5 | G79: =IF(F79<=Model!$B$24,"PAID","free with bundle") | H79: =VLOOKUP(E79,Model!$A$27:$B$35,2,FALSE) | I79: =MAX(Model!$B$22,H79-Model!$B$21) | J79: =H79-I79
A80: Paladin|Oath of Glory | B80: Paladin | C80: Oath of Glory | D80: Magic Weapon | E80: 2 | F80: 5 | G80: =IF(F80<=Model!$B$24,"PAID","free with bundle") | H80: =VLOOKUP(E80,Model!$A$27:$B$35,2,FALSE) | I80: =MAX(Model!$B$22,H80-Model!$B$21) | J80: =H80-I80
A81: Paladin|Oath of Glory | B81: Paladin | C81: Oath of Glory | D81: Haste | E81: 3 | F81: 9 | G81: =IF(F81<=Model!$B$24,"PAID","free with bundle") | H81: 0 | I81: 0 | J81: =H81-I81
A82: Paladin|Oath of Glory | B82: Paladin | C82: Oath of Glory | D82: Protection from Energy | E82: 3 | F82: 9 | G82: =IF(F82<=Model!$B$24,"PAID","free with bundle") | H82: 0 | I82: 0 | J82: =H82-I82
A83: Paladin|Oath of Glory | B83: Paladin | C83: Oath of Glory | D83: Compulsion | E83: 4 | F83: 13 | G83: =IF(F83<=Model!$B$24,"PAID","free with bundle") | H83: 0 | I83: 0 | J83: =H83-I83
A84: Paladin|Oath of Glory | B84: Paladin | C84: Oath of Glory | D84: Freedom of Movement | E84: 4 | F84: 13 | G84: =IF(F84<=Model!$B$24,"PAID","free with bundle") | H84: 0 | I84: 0 | J84: =H84-I84
A85: Paladin|Oath of Glory | B85: Paladin | C85: Oath of Glory | D85: Legend Lore | E85: 5 | F85: 17 | G85: =IF(F85<=Model!$B$24,"PAID","free with bundle") | H85: 0 | I85: 0 | J85: =H85-I85
A86: Paladin|Oath of Glory | B86: Paladin | C86: Oath of Glory | D86: Yolande's Regal Presence | E86: 5 | F86: 17 | G86: =IF(F86<=Model!$B$24,"PAID","free with bundle") | H86: 0 | I86: 0 | J86: =H86-I86
A87: Paladin|Oath of the Ancients | B87: Paladin | C87: Oath of the Ancients | D87: Ensnaring Strike | E87: 1 | F87: 3 | G87: =IF(F87<=Model!$B$24,"PAID","free with bundle") | H87: =VLOOKUP(E87,Model!$A$27:$B$35,2,FALSE) | I87: =MAX(Model!$B$22,H87-Model!$B$21) | J87: =H87-I87
A88: Paladin|Oath of the Ancients | B88: Paladin | C88: Oath of the Ancients | D88: Speak with Animals | E88: 1 | F88: 3 | G88: =IF(F88<=Model!$B$24,"PAID","free with bundle") | H88: =VLOOKUP(E88,Model!$A$27:$B$35,2,FALSE) | I88: =MAX(Model!$B$22,H88-Model!$B$21) | J88: =H88-I88
A89: Paladin|Oath of the Ancients | B89: Paladin | C89: Oath of the Ancients | D89: Misty Step | E89: 2 | F89: 5 | G89: =IF(F89<=Model!$B$24,"PAID","free with bundle") | H89: =VLOOKUP(E89,Model!$A$27:$B$35,2,FALSE) | I89: =MAX(Model!$B$22,H89-Model!$B$21) | J89: =H89-I89
A90: Paladin|Oath of the Ancients | B90: Paladin | C90: Oath of the Ancients | D90: Moonbeam | E90: 2 | F90: 5 | G90: =IF(F90<=Model!$B$24,"PAID","free with bundle") | H90: =VLOOKUP(E90,Model!$A$27:$B$35,2,FALSE) | I90: =MAX(Model!$B$22,H90-Model!$B$21) | J90: =H90-I90
A91: Paladin|Oath of the Ancients | B91: Paladin | C91: Oath of the Ancients | D91: Plant Growth | E91: 3 | F91: 9 | G91: =IF(F91<=Model!$B$24,"PAID","free with bundle") | H91: 0 | I91: 0 | J91: =H91-I91
A92: Paladin|Oath of the Ancients | B92: Paladin | C92: Oath of the Ancients | D92: Protection from Energy | E92: 3 | F92: 9 | G92: =IF(F92<=Model!$B$24,"PAID","free with bundle") | H92: 0 | I92: 0 | J92: =H92-I92
A93: Paladin|Oath of the Ancients | B93: Paladin | C93: Oath of the Ancients | D93: Ice Storm | E93: 4 | F93: 13 | G93: =IF(F93<=Model!$B$24,"PAID","free with bundle") | H93: 0 | I93: 0 | J93: =H93-I93
A94: Paladin|Oath of the Ancients | B94: Paladin | C94: Oath of the Ancients | D94: Stoneskin | E94: 4 | F94: 13 | G94: =IF(F94<=Model!$B$24,"PAID","free with bundle") | H94: 0 | I94: 0 | J94: =H94-I94
A95: Paladin|Oath of the Ancients | B95: Paladin | C95: Oath of the Ancients | D95: Commune with Nature | E95: 5 | F95: 17 | G95: =IF(F95<=Model!$B$24,"PAID","free with bundle") | H95: 0 | I95: 0 | J95: =H95-I95
A96: Paladin|Oath of the Ancients | B96: Paladin | C96: Oath of the Ancients | D96: Tree Stride | E96: 5 | F96: 17 | G96: =IF(F96<=Model!$B$24,"PAID","free with bundle") | H96: 0 | I96: 0 | J96: =H96-I96
A97: Paladin|Oath of Vengeance | B97: Paladin | C97: Oath of Vengeance | D97: Bane | E97: 1 | F97: 3 | G97: =IF(F97<=Model!$B$24,"PAID","free with bundle") | H97: =VLOOKUP(E97,Model!$A$27:$B$35,2,FALSE) | I97: =MAX(Model!$B$22,H97-Model!$B$21) | J97: =H97-I97
A98: Paladin|Oath of Vengeance | B98: Paladin | C98: Oath of Vengeance | D98: Hunter's Mark | E98: 1 | F98: 3 | G98: =IF(F98<=Model!$B$24,"PAID","free with bundle") | H98: =VLOOKUP(E98,Model!$A$27:$B$35,2,FALSE) | I98: =MAX(Model!$B$22,H98-Model!$B$21) | J98: =H98-I98
A99: Paladin|Oath of Vengeance | B99: Paladin | C99: Oath of Vengeance | D99: Hold Person | E99: 2 | F99: 5 | G99: =IF(F99<=Model!$B$24,"PAID","free with bundle") | H99: =VLOOKUP(E99,Model!$A$27:$B$35,2,FALSE) | I99: =MAX(Model!$B$22,H99-Model!$B$21) | J99: =H99-I99
A100: Paladin|Oath of Vengeance | B100: Paladin | C100: Oath of Vengeance | D100: Misty Step | E100: 2 | F100: 5 | G100: =IF(F100<=Model!$B$24,"PAID","free with bundle") | H100: =VLOOKUP(E100,Model!$A$27:$B$35,2,FALSE) | I100: =MAX(Model!$B$22,H100-Model!$B$21) | J100: =H100-I100
...

Sheet Bundles
A1: Class | B1: Subclass | C1: Paid spells | D1: Free spells | E1: Cross AP derived | F1: Origin AP derived | G1: Cross AP ENGINE | H1: Origin AP ENGINE | I1: Cross diff | J1: Origin diff | K1: Origin gap derived | L1: Origin gap ENGINE | M1: Is the discount applied twice? | N1: Derivation reproduces engine?
A2: Cleric | B2: Life Domain | C2: 6 | D2: 4 | E2: =SUMIFS('Per-spell working'!$H$2:$H$190,'Per-spell working'!$A$2:$A$190,"Cleric|Life Domain",'Per-spell working'!$G$2:$G$190,"PAID") | F2: =SUMIFS('Per-spell working'!$I$2:$I$190,'Per-spell working'!$A$2:$A$190,"Cleric|Life Domain",'Per-spell working'!$G$2:$G$190,"PAID") | G2: 8 | H2: 6 | I2: =G2-E2 | J2: =H2-F2 | K2: =E2-F2 | L2: =G2-H2 | M2: =IF(L2>K2,"YES - engine gap exceeds model",IF(L2=K2,"no - applied exactly once","no - applied LESS than once")) | N2: =IF(AND(I2=0,J2=0),"yes","NO")
A3: Cleric | B3: Light Domain | C3: 6 | D3: 4 | E3: =SUMIFS('Per-spell working'!$H$2:$H$190,'Per-spell working'!$A$2:$A$190,"Cleric|Light Domain",'Per-spell working'!$G$2:$G$190,"PAID") | F3: =SUMIFS('Per-spell working'!$I$2:$I$190,'Per-spell working'!$A$2:$A$190,"Cleric|Light Domain",'Per-spell working'!$G$2:$G$190,"PAID") | G3: 8 | H3: 6 | I3: =G3-E3 | J3: =H3-F3 | K3: =E3-F3 | L3: =G3-H3 | M3: =IF(L3>K3,"YES - engine gap exceeds model",IF(L3=K3,"no - applied exactly once","no - applied LESS than once")) | N3: =IF(AND(I3=0,J3=0),"yes","NO")
A4: Cleric | B4: Trickery Domain | C4: 6 | D4: 4 | E4: =SUMIFS('Per-spell working'!$H$2:$H$190,'Per-spell working'!$A$2:$A$190,"Cleric|Trickery Domain",'Per-spell working'!$G$2:$G$190,"PAID") | F4: =SUMIFS('Per-spell working'!$I$2:$I$190,'Per-spell working'!$A$2:$A$190,"Cleric|Trickery Domain",'Per-spell working'!$G$2:$G$190,"PAID") | G4: 8 | H4: 6 | I4: =G4-E4 | J4: =H4-F4 | K4: =E4-F4 | L4: =G4-H4 | M4: =IF(L4>K4,"YES - engine gap exceeds model",IF(L4=K4,"no - applied exactly once","no - applied LESS than once")) | N4: =IF(AND(I4=0,J4=0),"yes","NO")
A5: Cleric | B5: War Domain | C5: 6 | D5: 4 | E5: =SUMIFS('Per-spell working'!$H$2:$H$190,'Per-spell working'!$A$2:$A$190,"Cleric|War Domain",'Per-spell working'!$G$2:$G$190,"PAID") | F5: =SUMIFS('Per-spell working'!$I$2:$I$190,'Per-spell working'!$A$2:$A$190,"Cleric|War Domain",'Per-spell working'!$G$2:$G$190,"PAID") | G5: 8 | H5: 6 | I5: =G5-E5 | J5: =H5-F5 | K5: =E5-F5 | L5: =G5-H5 | M5: =IF(L5>K5,"YES - engine gap exceeds model",IF(L5=K5,"no - applied exactly once","no - applied LESS than once")) | N5: =IF(AND(I5=0,J5=0),"yes","NO")
A6: Druid | B6: Circle of the Land | C6: 4 | D6: 2 | E6: =SUMIFS('Per-spell working'!$H$2:$H$190,'Per-spell working'!$A$2:$A$190,"Druid|Circle of the Land",'Per-spell working'!$G$2:$G$190,"PAID") | F6: =SUMIFS('Per-spell working'!$I$2:$I$190,'Per-spell working'!$A$2:$A$190,"Druid|Circle of the Land",'Per-spell working'!$G$2:$G$190,"PAID") | G6: 8 | H6: 7 | I6: =G6-E6 | J6: =H6-F6 | K6: =E6-F6 | L6: =G6-H6 | M6: =IF(L6>K6,"YES - engine gap exceeds model",IF(L6=K6,"no - applied exactly once","no - applied LESS than once")) | N6: =IF(AND(I6=0,J6=0),"yes","NO")
A7: Druid | B7: Circle of the Moon | C7: 4 | D7: 2 | E7: =SUMIFS('Per-spell working'!$H$2:$H$190,'Per-spell working'!$A$2:$A$190,"Druid|Circle of the Moon",'Per-spell working'!$G$2:$G$190,"PAID") | F7: =SUMIFS('Per-spell working'!$I$2:$I$190,'Per-spell working'!$A$2:$A$190,"Druid|Circle of the Moon",'Per-spell working'!$G$2:$G$190,"PAID") | G7: 8 | H7: 7 | I7: =G7-E7 | J7: =H7-F7 | K7: =E7-F7 | L7: =G7-H7 | M7: =IF(L7>K7,"YES - engine gap exceeds model",IF(L7=K7,"no - applied exactly once","no - applied LESS than once")) | N7: =IF(AND(I7=0,J7=0),"yes","NO")
A8: Druid | B8: Circle of the Sea | C8: 7 | D8: 4 | E8: =SUMIFS('Per-spell working'!$H$2:$H$190,'Per-spell working'!$A$2:$A$190,"Druid|Circle of the Sea",'Per-spell working'!$G$2:$G$190,"PAID") | F8: =SUMIFS('Per-spell working'!$I$2:$I$190,'Per-spell working'!$A$2:$A$190,"Druid|Circle of the Sea",'Per-spell working'!$G$2:$G$190,"PAID") | G8: 11 | H8: 9 | I8: =G8-E8 | J8: =H8-F8 | K8: =E8-F8 | L8: =G8-H8 | M8: =IF(L8>K8,"YES - engine gap exceeds model",IF(L8=K8,"no - applied exactly once","no - applied LESS than once")) | N8: =IF(AND(I8=0,J8=0),"yes","NO")
A9: Druid | B9: Circle of the Stars | C9: 2 | D9: 0 | E9: =SUMIFS('Per-spell working'!$H$2:$H$190,'Per-spell working'!$A$2:$A$190,"Druid|Circle of the Stars",'Per-spell working'!$G$2:$G$190,"PAID") | F9: =SUMIFS('Per-spell working'!$I$2:$I$190,'Per-spell working'!$A$2:$A$190,"Druid|Circle of the Stars",'Per-spell working'!$G$2:$G$190,"PAID") | G9: 5 | H9: 5 | I9: =G9-E9 | J9: =H9-F9 | K9: =E9-F9 | L9: =G9-H9 | M9: =IF(L9>K9,"YES - engine gap exceeds model",IF(L9=K9,"no - applied exactly once","no - applied LESS than once")) | N9: =IF(AND(I9=0,J9=0),"yes","NO")
A10: Paladin | B10: Oath of Devotion | C10: 4 | D10: 6 | E10: =SUMIFS('Per-spell working'!$H$2:$H$190,'Per-spell working'!$A$2:$A$190,"Paladin|Oath of Devotion",'Per-spell working'!$G$2:$G$190,"PAID") | F10: =SUMIFS('Per-spell working'!$I$2:$I$190,'Per-spell working'!$A$2:$A$190,"Paladin|Oath of Devotion",'Per-spell working'!$G$2:$G$190,"PAID") | G10: 4 | H10: 4 | I10: =G10-E10 | J10: =H10-F10 | K10: =E10-F10 | L10: =G10-H10 | M10: =IF(L10>K10,"YES - engine gap exceeds model",IF(L10=K10,"no - applied exactly once","no - applied LESS than once")) | N10: =IF(AND(I10=0,J10=0),"yes","NO")
A11: Paladin | B11: Oath of Glory | C11: 4 | D11: 6 | E11: =SUMIFS('Per-spell working'!$H$2:$H$190,'Per-spell working'!$A$2:$A$190,"Paladin|Oath of Glory",'Per-spell working'!$G$2:$G$190,"PAID") | F11: =SUMIFS('Per-spell working'!$I$2:$I$190,'Per-spell working'!$A$2:$A$190,"Paladin|Oath of Glory",'Per-spell working'!$G$2:$G$190,"PAID") | G11: 4 | H11: 4 | I11: =G11-E11 | J11: =H11-F11 | K11: =E11-F11 | L11: =G11-H11 | M11: =IF(L11>K11,"YES - engine gap exceeds model",IF(L11=K11,"no - applied exactly once","no - applied LESS than once")) | N11: =IF(AND(I11=0,J11=0),"yes","NO")
A12: Paladin | B12: Oath of the Ancients | C12: 4 | D12: 6 | E12: =SUMIFS('Per-spell working'!$H$2:$H$190,'Per-spell working'!$A$2:$A$190,"Paladin|Oath of the Ancients",'Per-spell working'!$G$2:$G$190,"PAID") | F12: =SUMIFS('Per-spell working'!$I$2:$I$190,'Per-spell working'!$A$2:$A$190,"Paladin|Oath of the Ancients",'Per-spell working'!$G$2:$G$190,"PAID") | G12: 4 | H12: 4 | I12: =G12-E12 | J12: =H12-F12 | K12: =E12-F12 | L12: =G12-H12 | M12: =IF(L12>K12,"YES - engine gap exceeds model",IF(L12=K12,"no - applied exactly once","no - applied LESS than once")) | N12: =IF(AND(I12=0,J12=0),"yes","NO")
A13: Paladin | B13: Oath of Vengeance | C13: 4 | D13: 6 | E13: =SUMIFS('Per-spell working'!$H$2:$H$190,'Per-spell working'!$A$2:$A$190,"Paladin|Oath of Vengeance",'Per-spell working'!$G$2:$G$190,"PAID") | F13: =SUMIFS('Per-spell working'!$I$2:$I$190,'Per-spell working'!$A$2:$A$190,"Paladin|Oath of Vengeance",'Per-spell working'!$G$2:$G$190,"PAID") | G13: 4 | H13: 4 | I13: =G13-E13 | J13: =H13-F13 | K13: =E13-F13 | L13: =G13-H13 | M13: =IF(L13>K13,"YES - engine gap exceeds model",IF(L13=K13,"no - applied exactly once","no - applied LESS than once")) | N13: =IF(AND(I13=0,J13=0),"yes","NO")
A14: Ranger | B14: Fey Wanderer | C14: 2 | D14: 3 | E14: =SUMIFS('Per-spell working'!$H$2:$H$190,'Per-spell working'!$A$2:$A$190,"Ranger|Fey Wanderer",'Per-spell working'!$G$2:$G$190,"PAID") | F14: =SUMIFS('Per-spell working'!$I$2:$I$190,'Per-spell working'!$A$2:$A$190,"Ranger|Fey Wanderer",'Per-spell working'!$G$2:$G$190,"PAID") | G14: 2 | H14: 2 | I14: =G14-E14 | J14: =H14-F14 | K14: =E14-F14 | L14: =G14-H14 | M14: =IF(L14>K14,"YES - engine gap exceeds model",IF(L14=K14,"no - applied exactly once","no - applied LESS than once")) | N14: =IF(AND(I14=0,J14=0),"yes","NO")
A15: Ranger | B15: Gloom Stalker | C15: 2 | D15: 3 | E15: =SUMIFS('Per-spell working'!$H$2:$H$190,'Per-spell working'!$A$2:$A$190,"Ranger|Gloom Stalker",'Per-spell working'!$G$2:$G$190,"PAID") | F15: =SUMIFS('Per-spell working'!$I$2:$I$190,'Per-spell working'!$A$2:$A$190,"Ranger|Gloom Stalker",'Per-spell working'!$G$2:$G$190,"PAID") | G15: 2 | H15: 2 | I15: =G15-E15 | J15: =H15-F15 | K15: =E15-F15 | L15: =G15-H15 | M15: =IF(L15>K15,"YES - engine gap exceeds model",IF(L15=K15,"no - applied exactly once","no - applied LESS than once")) | N15: =IF(AND(I15=0,J15=0),"yes","NO")
A16: Sorcerer | B16: Aberrant Sorcery | C16: 7 | D16: 4 | E16: =SUMIFS('Per-spell working'!$H$2:$H$190,'Per-spell working'!$A$2:$A$190,"Sorcerer|Aberrant Sorcery",'Per-spell working'!$G$2:$G$190,"PAID") | F16: =SUMIFS('Per-spell working'!$I$2:$I$190,'Per-spell working'!$A$2:$A$190,"Sorcerer|Aberrant Sorcery",'Per-spell working'!$G$2:$G$190,"PAID") | G16: 12 | H16: 10 | I16: =G16-E16 | J16: =H16-F16 | K16: =E16-F16 | L16: =G16-H16 | M16: =IF(L16>K16,"YES - engine gap exceeds model",IF(L16=K16,"no - applied exactly once","no - applied LESS than once")) | N16: =IF(AND(I16=0,J16=0),"yes","NO")
A17: Sorcerer | B17: Clockwork Sorcery | C17: 6 | D17: 4 | E17: =SUMIFS('Per-spell working'!$H$2:$H$190,'Per-spell working'!$A$2:$A$190,"Sorcerer|Clockwork Sorcery",'Per-spell working'!$G$2:$G$190,"PAID") | F17: =SUMIFS('Per-spell working'!$I$2:$I$190,'Per-spell working'!$A$2:$A$190,"Sorcerer|Clockwork Sorcery",'Per-spell working'!$G$2:$G$190,"PAID") | G17: 8 | H17: 6 | I17: =G17-E17 | J17: =H17-F17 | K17: =E17-F17 | L17: =G17-H17 | M17: =IF(L17>K17,"YES - engine gap exceeds model",IF(L17=K17,"no - applied exactly once","no - applied LESS than once")) | N17: =IF(AND(I17=0,J17=0),"yes","NO")
A18: Sorcerer | B18: Draconic Sorcery | C18: 6 | D18: 4 | E18: =SUMIFS('Per-spell working'!$H$2:$H$190,'Per-spell working'!$A$2:$A$190,"Sorcerer|Draconic Sorcery",'Per-spell working'!$G$2:$G$190,"PAID") | F18: =SUMIFS('Per-spell working'!$I$2:$I$190,'Per-spell working'!$A$2:$A$190,"Sorcerer|Draconic Sorcery",'Per-spell working'!$G$2:$G$190,"PAID") | G18: 8 | H18: 6 | I18: =G18-E18 | J18: =H18-F18 | K18: =E18-F18 | L18: =G18-H18 | M18: =IF(L18>K18,"YES - engine gap exceeds model",IF(L18=K18,"no - applied exactly once","no - applied LESS than once")) | N18: =IF(AND(I18=0,J18=0),"yes","NO")
A19: Warlock | B19: Archfey Patron | C19: 7 | D19: 4 | E19: =SUMIFS('Per-spell working'!$H$2:$H$190,'Per-spell working'!$A$2:$A$190,"Warlock|Archfey Patron",'Per-spell working'!$G$2:$G$190,"PAID") | F19: =SUMIFS('Per-spell working'!$I$2:$I$190,'Per-spell working'!$A$2:$A$190,"Warlock|Archfey Patron",'Per-spell working'!$G$2:$G$190,"PAID") | G19: 9 | H19: 7 | I19: =G19-E19 | J19: =H19-F19 | K19: =E19-F19 | L19: =G19-H19 | M19: =IF(L19>K19,"YES - engine gap exceeds model",IF(L19=K19,"no - applied exactly once","no - applied LESS than once")) | N19: =IF(AND(I19=0,J19=0),"yes","NO")
A20: Warlock | B20: Celestial Patron | C20: 8 | D20: 4 | E20: =SUMIFS('Per-spell working'!$H$2:$H$190,'Per-spell working'!$A$2:$A$190,"Warlock|Celestial Patron",'Per-spell working'!$G$2:$G$190,"PAID") | F20: =SUMIFS('Per-spell working'!$I$2:$I$190,'Per-spell working'!$A$2:$A$190,"Warlock|Celestial Patron",'Per-spell working'!$G$2:$G$190,"PAID") | G20: 16 | H20: 14 | I20: =G20-E20 | J20: =H20-F20 | K20: =E20-F20 | L20: =G20-H20 | M20: =IF(L20>K20,"YES - engine gap exceeds model",IF(L20=K20,"no - applied exactly once","no - applied LESS than once")) | N20: =IF(AND(I20=0,J20=0),"yes","NO")
A21: Warlock | B21: Fiend Patron | C21: 6 | D21: 4 | E21: =SUMIFS('Per-spell working'!$H$2:$H$190,'Per-spell working'!$A$2:$A$190,"Warlock|Fiend Patron",'Per-spell working'!$G$2:$G$190,"PAID") | F21: =SUMIFS('Per-spell working'!$I$2:$I$190,'Per-spell working'!$A$2:$A$190,"Warlock|Fiend Patron",'Per-spell working'!$G$2:$G$190,"PAID") | G21: 8 | H21: 6 | I21: =G21-E21 | J21: =H21-F21 | K21: =E21-F21 | L21: =G21-H21 | M21: =IF(L21>K21,"YES - engine gap exceeds model",IF(L21=K21,"no - applied exactly once","no - applied LESS than once")) | N21: =IF(AND(I21=0,J21=0),"yes","NO")
A22: Warlock | B22: Great Old One Patron | C22: 6 | D22: 4 | E22: =SUMIFS('Per-spell working'!$H$2:$H$190,'Per-spell working'!$A$2:$A$190,"Warlock|Great Old One Patron",'Per-spell working'!$G$2:$G$190,"PAID") | F22: =SUMIFS('Per-spell working'!$I$2:$I$190,'Per-spell working'!$A$2:$A$190,"Warlock|Great Old One Patron",'Per-spell working'!$G$2:$G$190,"PAID") | G22: 8 | H22: 6 | I22: =G22-E22 | J22: =H22-F22 | K22: =E22-F22 | L22: =G22-H22 | M22: =IF(L22>K22,"YES - engine gap exceeds model",IF(L22=K22,"no - applied exactly once","no - applied LESS than once")) | N22: =IF(AND(I22=0,J22=0),"yes","NO")
A24: Subclasses of these classes that sell NO bundle - nothing to buy, no cost, no option
A25: Ranger | B25: Beast Master | G25: none | H25: none | M25: n/a - nothing to buy
A26: Ranger | B26: Hunter | G26: none | H26: none | M26: n/a - nothing to buy
A27: Sorcerer | B27: Wild Magic Sorcery | G27: none | H27: none | M27: n/a - nothing to buy
A29: Column M is the direct answer to 'is the origin discount applied twice?' - a doubled discount would make the ENGINE gap (L) exceed the model gap (K). It never does.

Sheet Price paths
A1: What the same buyer pays, by relationship to the class
A2: Verified by running compute(), not read off the source.
A4: Purchase | B4: Origin class | C4: Class unlocked, not origin | D4: Neither | E4: How that middle figure is reached
A5: Feature: Cleric: Blessed Strikes | B5: 10 | C5: 13 | D5: 17 | E5: sticker = cross - tier = 17 - 4 = 13
A6: Bundle: Cleric | Life Domain | B6: 6 | C6: 8 | D6: 8 | E6: no tier exists, so nothing is subtracted - it stays at cross = 8
A8: Column 3 of the guide's ability tables is the middle figure above and the bracket is the first - i.e.
A9: 'what a non-origin member of the class pays (what an origin member pays)'. Consistent in meaning.
A11: The real asymmetry: unlocking a class cuts 4 AP off that class's FEATURE (17 -> 13) but nothing off
A12: its BUNDLE (8 -> 8). Bundles have no sticker tier in the engine at all.
A14: As of DATA.version v0.347 a subclass purchase - ability or bundle - from a class you can neither
A15: build from nor have unlocked raises a blocking warning. Before that it was silently allowed, and
A16: because a bought bundle also claims that class's free subclass, no 15 AP unlock landed either.
A18: Neither table shows a discount applied twice. If it were, an Origin AP cell on the 'Per-spell
A19: working' sheet would fall below the 1 AP floor. None does.
